{
  "text-colour": {
    "default": {
      "default": {
        "value": "$neutral.100",
        "type": "color"
      },
      "highlight": {
        "value": "$generic.white",
        "type": "color"
      },
      "placeholder": {
        "value": "rbga ($neutral.100, 0.75)",
        "type": "color"
      },
      "disabled": {
        "value": "rbga ($neutral.100, 0.5)",
        "type": "color"
      },
      "success": {
        "value": "$sys.success.700",
        "type": "color"
      },
      "warning": {
        "value": "$sys.warning.700",
        "type": "color"
      },
      "error": {
        "value": "$sys.error.700",
        "type": "color"
      }
    }
  }
}